COPYING
MANIFEST.in
README
health_icu_view.xml
setup.py
./__init__.py
./health_icu.py
./health_icu_view.xml
./tryton.cfg
./doc/index.rst
./icons/gnuhealth_icu.svg
./locale/ar.po
./locale/de.po
./locale/el.po
./locale/es.po
./locale/fr.po
./locale/it_IT.po
./locale/ja_JP.po
./locale/lo.po
./locale/pt_BR.po
./locale/zh_CN.po
./tests/__init__.py
./tests/test_health_icu.py
./view/gnuhealth_icu_apache2_form.xml
./view/gnuhealth_icu_apache2_tree.xml
./view/gnuhealth_icu_chest_drainage_form.xml
./view/gnuhealth_icu_chest_drainage_tree.xml
./view/gnuhealth_icu_glasgow_form.xml
./view/gnuhealth_icu_glasgow_tree.xml
./view/gnuhealth_icu_ventilation_form.xml
./view/gnuhealth_icu_ventilation_tree.xml
./view/gnuhealth_inpatient_icu_form.xml
./view/gnuhealth_inpatient_icu_tree.xml
./view/gnuhealth_patient_icu_rounding.xml
icons/README
icons/gnuhealth_icu.svg
locale/ar.po
locale/de.po
locale/el.po
locale/es.po
locale/fr.po
locale/it_IT.po
locale/ja_JP.po
locale/lo.po
locale/pt_BR.po
locale/zh_CN.po
security/access_rights.xml
trytond_health_icu.egg-info/PKG-INFO
trytond_health_icu.egg-info/SOURCES.txt
trytond_health_icu.egg-info/dependency_links.txt
trytond_health_icu.egg-info/entry_points.txt
trytond_health_icu.egg-info/not-zip-safe
trytond_health_icu.egg-info/requires.txt
trytond_health_icu.egg-info/top_level.txt
view/gnuhealth_icu_apache2_form.xml
view/gnuhealth_icu_apache2_tree.xml
view/gnuhealth_icu_chest_drainage_form.xml
view/gnuhealth_icu_chest_drainage_tree.xml
view/gnuhealth_icu_glasgow_form.xml
view/gnuhealth_icu_glasgow_tree.xml
view/gnuhealth_icu_ventilation_form.xml
view/gnuhealth_icu_ventilation_tree.xml
view/gnuhealth_inpatient_icu_form.xml
view/gnuhealth_inpatient_icu_tree.xml
view/gnuhealth_patient_icu_rounding.xml